mrd/__init__.py
mrd-0.0.1.dist-info/LICENSE
mrd-0.0.1.dist-info/WHEEL
mrd-0.0.1.dist-info/METADATA
mrd-0.0.1.dist-info/RECORD
